setup.py
src/nose_bisect/__init__.py
src/nose_bisect/colors.py
src/nose_bisect/plugin.py
src/nose_bisect.egg-info/PKG-INFO
src/nose_bisect.egg-info/SOURCES.txt
src/nose_bisect.egg-info/dependency_links.txt
src/nose_bisect.egg-info/entry_points.txt
src/nose_bisect.egg-info/not-zip-safe
src/nose_bisect.egg-info/requires.txt
src/nose_bisect.egg-info/top_level.txt