Metadata-Version: 1.0
Name: nose-bisect
Version: 0.1.0
Summary: A Nose plugin which allows bisection of test failures.
Home-page: http://github.com/dcramer/nose-bisect
Author: David Cramer
Author-email: dcramer@gmail.com
License: Apache License 2.0
Platform: UNKNOWN
Classifier: Intended Audience :: Developers
Classifier: Intended Audience :: System Administrators
Classifier: Operating System :: OS Independent
Classifier: Topic :: Software Development
